<?xml version="1.0"?>
<libraries>
    <library>
        <location>Captioning/</location>
        <name>captioning/captioning</name>
        <version>2.6.0</version>
        <license>MIT</license>
        <licenseversion></licenseversion>
    </library>
    <library>
        <location>lib/</location>
        <license>MIT</license>
        <name>bootstrap</name>
    </library>
    <library>
        <!-- Generated by enyojs -->
        <location>package.js</location>
        <license>Apache</license>
        <name>package</name>
    </library>
    <library>
        <!-- Generated by enyojs -->
        <location>build/enyo.css</location>
        <license>Apache</license>
        <name>enyo.css</name>
    </library>
    <library>
        <!-- Generated by enyojs -->
        <location>build/enyo.js</location>
        <license>Apache</license>
        <name>enyo.js</name>
    </library>
    <library>
        <!-- Generated by enyojs -->
        <location>build/app.css</location>
        <name>app.css</name>
        <license>CeCILL-B</license>
    </library>
    <library>
        <!-- Generated by enyojs -->
        <location>build/app.js</location>
        <name>app.js</name>
        <license>CeCILL-B</license>
    </library>
</libraries>
